smoid/SignalControl.py
smoid/__init__.py
smoid/__main__.py
smoid-0.0.1.dist-info/LICENSE
smoid-0.0.1.dist-info/METADATA
smoid-0.0.1.dist-info/WHEEL
smoid-0.0.1.dist-info/top_level.txt
smoid-0.0.1.dist-info/RECORD
