Metadata-Version: 2.1
Name: smoid
Version: 0.0.1
Summary: smoid is a package that allows you to monitor signals from a machine and send them to a server.
Author: Cesar
Author-email: unit@noreply.com
License: MIT License
License-File: LICENSE
